radtrun/__init__.py
radtrun/__main__.py
radtrun/mldgpu.py
radtrun/radtrun.py
radtrun/listeners/__init__.py
radtrun/listeners/dcgmi_listener.py
radtrun/listeners/ps_listener.py
radtrun/listeners/smi_listener.py
radtrun/listeners/top_listener.py
radtrun-0.1.3.dist-info/WHEEL
radtrun-0.1.3.dist-info/METADATA
radtrun-0.1.3.dist-info/RECORD
