Metadata-Version: 2.1
Name: radtrun
Version: 0.1.3
Summary: Runner for Resource-Aware Data systems Tracker (radT) for automatically tracking and training machine learning software
Author-email: Ties Robroek <titr@itu.dk>
Classifier: License :: OSI Approved :: MIT License
Project-URL: Home, https://github.com/Resource-Aware-Data-systems-RAD/radt
